{"factuur": {"factuur-nummer": "2011-783", "factuur-datum": "2020-06-09", "uiterlijke-betaal-datum": "2020-09-07", "klant": {"naam": "PC Saturnus B.V.", "address": "Schoolstraat 870", "postcode": "6790 AC", "plaats": "Amsterdam"}, "producten": [{"product-naam": "Oracle Cloud", "aantal": 4, "prijs-per-stuk": 392.3, "totale-prijs-excl": 1569.2, "totale-prijs-incl": 1710.43}, {"product-naam": "Adobe Premiere Pro", "aantal": 3, "prijs-per-stuk": 442.41, "totale-prijs-excl": 1327.23, "totale-prijs-incl": 1446.68}, {"product-naam": "Adobe Creative Cloud", "aantal": 4, "prijs-per-stuk": 433.34, "totale-prijs-excl": 1733.36, "totale-prijs-incl": 1837.36}, {"product-naam": "Microsoft Dynamics 365", "aantal": 5, "prijs-per-stuk": 178.52, "totale-prijs-excl": 892.6, "totale-prijs-incl": 972.93}, {"product-naam": "Microsoft Windows Server 2019", "aantal": 2, "prijs-per-stuk": 456.9, "totale-prijs-excl": 913.8, "totale-prijs-incl": 996.04}]}}