{"factuur": {"factuur-nummer": "2019-609", "factuur-datum": "2023-06-17", "uiterlijke-betaal-datum": "2023-09-15", "klant": {"naam": "PC Jupiter B.V.", "address": "Schoolstraat 3", "postcode": "2690 AC", "plaats": "Utrecht"}, "producten": [{"product-naam": "Oracle VM", "aantal": 4, "prijs-per-stuk": 187.01, "totale-prijs-excl": 748.04, "totale-prijs-incl": 792.92}, {"product-naam": "Oracle Cloud", "aantal": 4, "prijs-per-stuk": 471.26, "totale-prijs-excl": 1885.04, "totale-prijs-incl": 2054.69}]}}